parallel_codex/__init__.py
parallel_codex/cli.py
parallel_codex/core.py
parallel_codex/pcodex.py
parallel_codex/commands/__init__.py
parallel_codex/commands/list_worktrees.py
parallel_codex/commands/plan.py
parallel_codex/commands/prune.py
parallel_codex-0.1.2.dist-info/METADATA
parallel_codex-0.1.2.dist-info/WHEEL
parallel_codex-0.1.2.dist-info/entry_points.txt
parallel_codex-0.1.2.dist-info/RECORD
