Metadata-Version: 2.4
Name: parallel-codex
Version: 0.1.2
Summary: Python toolkit for orchestrating Parallel Codex agents across isolated worktrees.
Project-URL: Homepage, https://github.com/parallel-codex/parallel-codex
Project-URL: Issues, https://github.com/parallel-codex/parallel-codex/issues
Project-URL: Repository, https://github.com/parallel-codex/parallel-codex.git
Project-URL: Documentation, https://github.com/parallel-codex/parallel-codex/tree/main/packages/python-package
Author-email: Parallel Codex Team <alejandro.quiros3101@gmail.com>
License: MIT
Keywords: agents,automation,codex,git,worktree
Classifier: Development Status :: 3 - Alpha
Classifier: Intended Audience :: Developers
Classifier: License :: OSI Approved :: MIT License
Classifier: Programming Language :: Python :: 3
Classifier: Programming Language :: Python :: 3.11
Classifier: Programming Language :: Python :: 3.12
Classifier: Programming Language :: Python :: 3.13
Requires-Python: >=3.11
Provides-Extra: dev
Requires-Dist: mypy>=1.7.0; extra == 'dev'
Requires-Dist: pytest-cov>=4.1.0; extra == 'dev'
Requires-Dist: pytest>=8.0.0; extra == 'dev'
Requires-Dist: ruff>=0.1.0; extra == 'dev'
